{
	"trail_effects": [
		{
			"start_time": 3.3,
			"end_time": 3.5,
			"joint": "Tool_R",
			"item_skin_hand": "main_hand"
		},
		{
			"start_time": 4.4,
			"end_time": 4.6,
			"joint": "Tool_R",
			"item_skin_hand": "main_hand"
		},
		{
			"start_time": 5.3,
			"end_time": 5.6,
			"joint": "Tool_R",
			"item_skin_hand": "main_hand"
		},
		{
			"start_time": 6.3,
			"end_time": 6.6,
			"joint": "Tool_R",
			"item_skin_hand": "main_hand"
		},
		{
			"start_time": 7.4,
			"end_time": 7.6,
			"joint": "Tool_R",
			"item_skin_hand": "main_hand"
		}
	]
}